genbadge/__init__.py
genbadge/_version.py
genbadge/badge-template.svg
genbadge/main.py
genbadge/py.typed
genbadge/utils_badge.py
genbadge/utils_coverage.py
genbadge/utils_flake8.py
genbadge/utils_junit.py
genbadge/verdana.ttf
genbadge/xunitparser_copy.py
genbadge-1.1.1.dist-info/LICENSE
genbadge-1.1.1.dist-info/METADATA
genbadge-1.1.1.dist-info/WHEEL
genbadge-1.1.1.dist-info/entry_points.txt
genbadge-1.1.1.dist-info/top_level.txt
genbadge-1.1.1.dist-info/RECORD
