Metadata-Version: 2.1
Name: genbadge
Version: 1.1.1
Summary: Generate badges for tools that do not provide one.
Home-page: https://github.com/smarie/python-genbadge
Download-URL: https://github.com/smarie/python-genbadge/tarball/1.1.1
Author: Sylvain MARIE <sylvain.marie@se.com>
Maintainer: Sylvain MARIE <sylvain.marie@se.com>
License: BSD 3-Clause
Keywords: commandline cli generate badge shield svg flake8 pytest test coverage markdown
Classifier: Development Status :: 5 - Production/Stable
Classifier: Intended Audience :: Education
Classifier: Intended Audience :: Developers
Classifier: Intended Audience :: Information Technology
Classifier: License :: OSI Approved :: BSD License
Classifier: Topic :: Software Development :: Libraries :: Python Modules
Classifier: Programming Language :: Python
Classifier: Programming Language :: Python :: 2
Classifier: Programming Language :: Python :: 2.7
Classifier: Programming Language :: Python :: 3
Classifier: Programming Language :: Python :: 3.5
Classifier: Programming Language :: Python :: 3.6
Classifier: Programming Language :: Python :: 3.7
Classifier: Programming Language :: Python :: 3.8
Classifier: Programming Language :: Python :: 3.9
Provides-Extra: tests
Provides-Extra: coverage
Provides-Extra: flake8
Provides-Extra: all
License-File: LICENSE
